pyqna/__init__.py
pyqna/_version.py
pyqna/datasets/__init__.py
pyqna/datasets/open_domain/__init__.py
pyqna/datasets/reading_comprehension/__init__.py
pyqna/metrics/__init__.py
pyqna/models/__init__.py
pyqna/models/base.py
pyqna/models/open_domain/__init__.py
pyqna/models/reading_comprehension/__init__.py
pyqna/models/reading_comprehension/transformer_models.py
pyqna/tests/__init__.py
pyqna/tests/conftest.py
pyqna/tests/test_examples.py
pyqna/utils/__init__.py
pyqna/utils/logging.py
pyqna-0.0.4.dist-info/AUTHORS.rst
pyqna-0.0.4.dist-info/LICENSE
pyqna-0.0.4.dist-info/METADATA
pyqna-0.0.4.dist-info/WHEEL
pyqna-0.0.4.dist-info/entry_points.txt
pyqna-0.0.4.dist-info/top_level.txt
pyqna-0.0.4.dist-info/RECORD
