Metadata-Version: 2.1
Name: pyqna
Version: 0.0.4
Summary: A simple python package for question answering
Home-page: https://github.com/programmer290399/pyqna
Author: Saahil Ali
Author-email: programmer290399@gmail.com
License: BSD (3-clause)
Platform: UNKNOWN
Classifier: Development Status :: 2 - Pre-Alpha
Classifier: Natural Language :: English
Classifier: Programming Language :: Python :: 3
Requires-Python: >=3.7
License-File: LICENSE
License-File: AUTHORS.rst
Provides-Extra: all
Requires-Dist: transformers ; extra == 'all'
Requires-Dist: torch ; extra == 'all'
Provides-Extra: torch
Requires-Dist: torch ; extra == 'torch'
Provides-Extra: transformers
Requires-Dist: transformers ; extra == 'transformers'
Requires-Dist: torch ; extra == 'transformers'
